alu.v
module alu(
    input [31:0] src1,
    input [31:0] src2,
    input [3:0] op,
    output reg [31:0] result 
);

    always @(*) begin
        case (op)
            4'b0000: result = src1 + src2;   // ADD
            4'b0001: result = src1 - src2;   // SUB
            4'b0010: result = src1 * src2;   // MUL
            default: result = 0;
        endcase
    end
endmodule


//Each instruction is 32bits.
//ADD r1, r2 ->r3  	// Add two registers
//SUB r1, r2 ->r3  	// Subtract two registers
//MUL r1, r2->3	// Multiply two registers
//LDB 80(r1) ->r0  	// Load Byte; base register + offset
//LDW 80(r1) ->r0 	// Load Word; base register + offset
//STB r0 ->80(r1) 	// Store Byte; base register + offset
//STW r0 ->80(r1) 	// Store Word; base register + offset
//BEQ r1, offset 	// if r1==r2, PC=PC+offset
//JUMP r1, offset	// PC = r1 + offset
//
//OPCODES
//

reg32.v
module reg32(
	input [31:0] inData, 
	input clk, 
	input enable, 
	input reset, 
	output reg [31:0] outData
);
	
	always @(posedge clk or posedge reset) begin
		if (reset)
			outData <= 32'b0;
		else if (enable)
			//$display("    Reg Changed: %d", inData);
			outData <= inData;

		$display("Reg Changed: %d -> %d", outData, inData);
	end

endmodule

clock.v
`timescale 1ns/1ps

module clock(output reg clk);

	parameter PERIOD = 1;
	integer cycle = -1;
	initial begin
		clk <= 0;
		$monitor("Clk: $d", cycle);
		//while (true)
	end 

	always begin
		cycle <= cycle + 1;
		$display("Cycle: $d", cycle);
		#(PERIOD / 2) clk = ~clk; // invert clk
	end

endmodule

processor_tb.v
`include "clock.v"
`include "reg32.v"
`include "alu.v"

module processor_tb;

// Declare the clock signal
wire clk;

// Instantiate the clock generator
clock #(.PERIOD(2)) clk_gen (
	.clk(clk)
);



reg reset = 0;
reg enable = 1;
// ALU and register signals
reg [31:0] inData1, inData2;       // ALU inputs before loading into reg32
reg [3:0] op;                      // ALU operation code
wire [31:0] src1, src2;      // Outputs of reg32 modules, inputs to ALU
wire [31:0] aluResult;             // ALU output
wire [31:0] finalResult;           // Output of reg32 for the ALU result

// Instantiate reg32 modules for ALU inputs and output
reg32 reg1 (
    .inData(inData1),
    .clk(clk),
    .enable(enable),
    .reset(reset),
    .outData(src1)
);

reg32 reg2 (
    .inData(inData2),
    .clk(clk),
    .enable(enable),
    .reset(reset),
    .outData(src2)
);

reg32 resultReg (
    .inData(aluResult),
    .clk(clk),
    .enable(enable),
    .reset(reset),
    .outData(finalResult)
);

// Instantiate the ALU, using reg32 outputs as inputs
alu alu_inst (
    .src1(src1),
    .src2(src2),
    .op(op),
    .result(aluResult)
);



initial begin
    $dumpfile("computation.vcd");
    $dumpvars(0, processor_tb);
    
    // Display header
    $display("Testing ALU Operations with reg32");
    $monitor("Time=%0t | src1=%d | src2=%d | op=%b | aluResult=%d | finalResult=%d",
              $time, src1, src2, op, aluResult, finalResult);

    //ADD
    $display("Adding");
    inData1 = 10;
    inData2 = 5;
    op = 4'b0000; // ADD operation
    #4; // Wait for registers to latch inputs
    if (finalResult !== 15) $display("ADD failed: Expected 15, got %d", finalResult);
    
    
    //SUB
    $display("Subtracting");
    inData1 = 20;
    inData2 = 10;
    op = 4'b0001; // SUB operation
    #4;
    if (finalResult !== 10) $display("SUB failed: Expected 15, got %d", finalResult);

    //MUL
    $display("Multiplying");
    inData1 = 5;
    inData2 = 6;
    op = 4'b0010; // MUL operation
    #4;
    if (finalResult !== 30) $display("MUL failed: Expected 12, got %d", finalResult);

    #2 $finish;
end

endmodule

computation.vcd
$date
	Wed Oct 30 17:30:34 2024
$end
$version
	Icarus Verilog
$end
$timescale
	1ps
$end
$scope module processor_tb $end
$var wire 32 ! src2 [31:0] $end
$var wire 32 " src1 [31:0] $end
$var wire 32 # finalResult [31:0] $end
$var wire 1 $ clk $end
$var wire 32 % aluResult [31:0] $end
$var reg 1 & enable $end
$var reg 32 ' inData1 [31:0] $end
$var reg 32 ( inData2 [31:0] $end
$var reg 4 ) op [3:0] $end
$var reg 1 * reset $end
$scope module alu_inst $end
$var wire 4 + op [3:0] $end
$var wire 32 , src2 [31:0] $end
$var wire 32 - src1 [31:0] $end
$var reg 32 . result [31:0] $end
$upscope $end
$scope module clk_gen $end
$var parameter 32 / PERIOD $end
$var reg 1 $ clk $end
$var integer 32 0 cycle [31:0] $end
$upscope $end
$scope module reg1 $end
$var wire 1 $ clk $end
$var wire 1 & enable $end
$var wire 32 1 inData [31:0] $end
$var wire 1 * reset $end
$var reg 32 2 outData [31:0] $end
$upscope $end
$scope module reg2 $end
$var wire 1 $ clk $end
$var wire 1 & enable $end
$var wire 32 3 inData [31:0] $end
$var wire 1 * reset $end
$var reg 32 4 outData [31:0] $end
$upscope $end
$scope module resultReg $end
$var wire 1 $ clk $end
$var wire 1 & enable $end
$var wire 32 5 inData [31:0] $end
$var wire 1 * reset $end
$var reg 32 6 outData [31:0] $end
$upscope $end
$upscope $end
$enddefinitions $end
$comment Show the parameter values. $end
$dumpall
b10 /
$end
#0
$dumpvars
bx 6
bx 5
bx 4
b101 3
bx 2
b1010 1
b0 0
bx .
bx -
bx ,
b0 +
0*
b0 )
b101 (
b1010 '
1&
bx %
0$
bx #
bx "
bx !
$end
#1000
b1111 %
b1111 .
b1111 5
b1010 "
b1010 -
b1010 2
b101 !
b101 ,
b101 4
b1 0
1$
#2000
b10 0
0$
#3000
b1111 #
b1111 6
b11 0
1$
#4000
b100 0
b101 %
b101 .
b101 5
0$
b1 )
b1 +
b1010 (
b1010 3
b10100 '
b10100 1
#5000
b1010 %
b1010 .
b1010 5
b10100 "
b10100 -
b10100 2
b1010 !
b1010 ,
b1010 4
b101 #
b101 6
b101 0
1$
#6000
b110 0
0$
#7000
b1010 #
b1010 6
b111 0
1$
#8000
b1000 0
b11001000 %
b11001000 .
b11001000 5
0$
b10 )
b10 +
b110 (
b110 3
b101 '
b101 1
#9000
b11110 %
b11110 .
b11110 5
b101 "
b101 -
b101 2
b110 !
b110 ,
b110 4
b11001000 #
b11001000 6
b1001 0
1$
#10000
b1010 0
0$
#11000
b11110 #
b11110 6
b1011 0
1$
#12000
b1100 0
0$
#13000
b1101 0
1$
#14000
b1110 0
0$
